russian_paraphrasers/__init__.py
russian_paraphrasers/candidates_filter_metrics.py
russian_paraphrasers/utils.py
russian_paraphrasers/paraphrasers/__init__.py
russian_paraphrasers/paraphrasers/core.py
russian_paraphrasers/paraphrasers/paraphraser_gpt.py
russian_paraphrasers/paraphrasers/paraphraser_mt5.py
russian_paraphrasers-0.0.3.dist-info/LICENSE
russian_paraphrasers-0.0.3.dist-info/METADATA
russian_paraphrasers-0.0.3.dist-info/WHEEL
russian_paraphrasers-0.0.3.dist-info/dependency_links.txt
russian_paraphrasers-0.0.3.dist-info/top_level.txt
russian_paraphrasers-0.0.3.dist-info/RECORD
