Metadata-Version: 2.1
Name: russian-paraphrasers
Version: 0.0.3
Summary: Russian Paraphrasers (based on ru-gpt, mt5)
Home-page: https://github.com/RussianNLP/russian_paraphrasers
Author: Alenusch
Author-email: alenush93@gmail.com
License: UNKNOWN
Platform: UNKNOWN
Classifier: Programming Language :: Python :: 3
Classifier: License :: OSI Approved :: MIT License
Classifier: Operating System :: OS Independent
Requires-Dist: nltk
Requires-Dist: scipy
Requires-Dist: transformers (>=4.0.1)
Requires-Dist: sentence-transformers (==0.4.0)
